{"type":"FeatureCollection","features":[{"type":"Feature","properties":{"id":"b8d88b1459d7056dc4872899","name":"新北市立圖書館坪林分館","category":"library","facilityType":"public-library","sourceUpdatedAt":"2026-07-21T02:59:00.336Z"},"geometry":{"type":"Point","coordinates":[121.7127,24.9371]}}]}
