{"type":"FeatureCollection","features":[{"type":"Feature","properties":{"id":"baadaa71281c8e93ffd8a49f","name":"臺北市立聯合醫院","category":"medical","facilityType":"hospital","sourceUpdatedAt":"2026-07-21T02:58:29.534Z"},"geometry":{"type":"Point","coordinates":[121.5088874,25.05069244]}}]}
