{"type":"FeatureCollection","features":[{"type":"Feature","properties":{"id":"aa35f72b1912cceef5500b43","name":"臺北市立圖書館中山分館","category":"library","facilityType":"public-library","sourceUpdatedAt":"2026-07-21T02:59:00.336Z"},"geometry":{"type":"Point","coordinates":[121.5336,25.0642]}},{"type":"Feature","properties":{"id":"89695c16cf7fa2875ef3c54c","name":"臺北市立圖書館長安分館","category":"library","facilityType":"public-library","sourceUpdatedAt":"2026-07-21T02:59:00.336Z"},"geometry":{"type":"Point","coordinates":[121.5209,25.0501]}},{"type":"Feature","properties":{"id":"355b53c594ee11c1c5228f49","name":"臺北市立圖書館大直分館","category":"library","facilityType":"public-library","sourceUpdatedAt":"2026-07-21T02:59:00.336Z"},"geometry":{"type":"Point","coordinates":[121.5467,25.0819]}},{"type":"Feature","properties":{"id":"b60944d5ef0a8999e969c377","name":"臺北市立圖書館恆安民眾閱覽室","category":"library","facilityType":"public-library","sourceUpdatedAt":"2026-07-21T02:59:00.336Z"},"geometry":{"type":"Point","coordinates":[121.527201,25.063438]}}]}
