{"type":"FeatureCollection","features":[{"type":"Feature","properties":{"name":"新店","category":"metro"},"geometry":{"type":"Point","coordinates":[121.53746,24.95761]}},{"type":"Feature","properties":{"name":"新店區公所","category":"metro"},"geometry":{"type":"Point","coordinates":[121.5413,24.96744]}},{"type":"Feature","properties":{"name":"七張","category":"metro"},"geometry":{"type":"Point","coordinates":[121.542985,24.97545]}},{"type":"Feature","properties":{"name":"小碧潭","category":"metro"},"geometry":{"type":"Point","coordinates":[121.53058,24.97188]}},{"type":"Feature","properties":{"name":"大坪林","category":"metro"},"geometry":{"type":"Point","coordinates":[121.54134,24.9827205]}}]}
