{"type":"FeatureCollection","features":[{"type":"Feature","properties":{"name":"觀光大橋","category":"bus"},"geometry":{"type":"Point","coordinates":[121.5488274,24.869041]}},{"type":"Feature","properties":{"name":"堰堤","category":"bus"},"geometry":{"type":"Point","coordinates":[121.547669,24.87103]}},{"type":"Feature","properties":{"name":"巨龍山莊","category":"bus"},"geometry":{"type":"Point","coordinates":[121.5474005,24.874297]}},{"type":"Feature","properties":{"name":"污水處理廠","category":"bus"},"geometry":{"type":"Point","coordinates":[121.544285,24.875842]}},{"type":"Feature","properties":{"name":"成功","category":"bus"},"geometry":{"type":"Point","coordinates":[121.54267,24.880888]}},{"type":"Feature","properties":{"name":"加九寮","category":"bus"},"geometry":{"type":"Point","coordinates":[121.5438922,24.883668]}},{"type":"Feature","properties":{"name":"桶壁公園","category":"bus"},"geometry":{"type":"Point","coordinates":[121.545406,24.884124]}},{"type":"Feature","properties":{"name":"桶壁","category":"bus"},"geometry":{"type":"Point","coordinates":[121.547466,24.883857]}},{"type":"Feature","properties":{"name":"隧道口","category":"bus"},"geometry":{"type":"Point","coordinates":[121.5513702,24.890176]}},{"type":"Feature","properties":{"name":"污水處理廠","category":"bus"},"geometry":{"type":"Point","coordinates":[121.544155,24.875646]}},{"type":"Feature","properties":{"name":"桶壁","category":"bus"},"geometry":{"type":"Point","coordinates":[121.547701,24.884049]}},{"type":"Feature","properties":{"name":"桶壁公園","category":"bus"},"geometry":{"type":"Point","coordinates":[121.5455189,24.884211]}},{"type":"Feature","properties":{"name":"加九寮","category":"bus"},"geometry":{"type":"Point","coordinates":[121.5437044,24.883456]}},{"type":"Feature","properties":{"name":"成功","category":"bus"},"geometry":{"type":"Point","coordinates":[121.542472,24.880405]}},{"type":"Feature","properties":{"name":"堰堤","category":"bus"},"geometry":{"type":"Point","coordinates":[121.547599,24.871217]}},{"type":"Feature","properties":{"name":"巨龍山莊","category":"bus"},"geometry":{"type":"Point","coordinates":[121.5472288,24.874093]}},{"type":"Feature","properties":{"name":"觀光大橋","category":"bus"},"geometry":{"type":"Point","coordinates":[121.549734,24.868349]}},{"type":"Feature","properties":{"name":"烏來","category":"bus"},"geometry":{"type":"Point","coordinates":[121.5511543,24.866576]}}]}
